dysonclient/__init__.py
dysonclient/dysonclient.py
dysonclient/entities.py
dysonclient/log_pb2.py
dysonclient/log_pb2_grpc.py
dysonclient-0.0.7.dist-info/METADATA
dysonclient-0.0.7.dist-info/WHEEL
dysonclient-0.0.7.dist-info/top_level.txt
dysonclient-0.0.7.dist-info/RECORD
